.DS_Store
hedm_pre/HEDM_Pre.py
hedm_pre/__init__.py
hedm_pre/hello_world.py
hedm_pre/data/imaged11_dx.edf
hedm_pre/data/imaged11_dy.edf
hedm_pre/scripts/clean_flt.py
hedm_pre/scripts/fitting.py
hedm_pre/scripts/gen_flt.py
hedm_pre/scripts/hello_world.py
hedm_pre/scripts/indexing.py
hedm_pre/scripts/sparse_h5.py
hedm_pre-0.1.1.dist-info/METADATA
hedm_pre-0.1.1.dist-info/WHEEL
hedm_pre-0.1.1.dist-info/entry_points.txt
hedm_pre-0.1.1.dist-info/top_level.txt
hedm_pre-0.1.1.dist-info/RECORD
