Metadata-Version: 2.1
Name: hedm-pre
Version: 0.1.1
Summary: Tools for pre-processing data for High Energy Diffraction Microscopy (HEDM) analysis
Home-page: https://github.com/minety/HEDM
Author: Ye Tian
Author-email: ytian37@jhu.edu
Classifier: Development Status :: 3 - Alpha
Classifier: Intended Audience :: Science/Research
Classifier: License :: OSI Approved :: BSD License
Classifier: Programming Language :: Python :: 3
Classifier: Programming Language :: Python :: 3.8
Classifier: Programming Language :: Python :: 3.9
Requires-Python: >=3.8
